LICENSE
README.md
setup.py
map_address/__init__.py
map_address/__main__.py
map_address/map_it.py
map_address.egg-info/PKG-INFO
map_address.egg-info/SOURCES.txt
map_address.egg-info/dependency_links.txt
map_address.egg-info/entry_points.txt
map_address.egg-info/top_level.txt