Metadata-Version: 1.0
Name: map-address
Version: 0.1.0
Summary: An application to open a map address in a web browser from commandline or clipboard
Home-page: https://github.com/muckswon-1/muckswon-1
Author: Cyril Mukabwa
Author-email: mukabwacyril@gmail.com
License: UNKNOWN
Platform: UNKNOWN
